[
  {
    "Name": "Test",
    "Source": "C:\\Users\\euphr\\Pictures",
    "Cible": "C:\\ppp",
    "Type": "Complet",
    "Status": "Terminé"
  },
  {
    "Name": "Test2",
    "Source": "C:\\Users\\euphr\\Videos",
    "Cible": "C:\\Videos",
    "Type": "Complet",
    "Status": null
  },
  {
    "Name": "test54",
    "Source": "c:\\source",
    "Cible": "c:\\cible",
    "Type": "Complet",
    "Status": "Created"
  },
  {
    "Name": "testtt",
    "Source": "C:\\tesst",
    "Cible": "C:\\test-2",
    "Type": "Complet",
    "Status": "Created"
  }
]